mktree.py
modularizer_mktree-0.2.0.dist-info/licenses/LICENSE
modularizer_mktree-0.2.0.dist-info/METADATA
modularizer_mktree-0.2.0.dist-info/WHEEL
modularizer_mktree-0.2.0.dist-info/entry_points.txt
modularizer_mktree-0.2.0.dist-info/top_level.txt
modularizer_mktree-0.2.0.dist-info/RECORD
