Metadata-Version: 2.4
Name: modularizer-mktree
Version: 0.2.0
Summary: Create directory trees from a tree specification
Author-email: Torin Halsted <modularizer@gmail.com>
License: Unlicense
Keywords: directory,tree,filesystem,cli
Classifier: Development Status :: 3 - Alpha
Classifier: Intended Audience :: Developers
Classifier: License :: Public Domain
Classifier: Programming Language :: Python :: 3
Classifier: Programming Language :: Python :: 3.8
Classifier: Programming Language :: Python :: 3.9
Classifier: Programming Language :: Python :: 3.10
Classifier: Programming Language :: Python :: 3.11
Classifier: Programming Language :: Python :: 3.12
Classifier: Topic :: Software Development :: Libraries :: Python Modules
Classifier: Topic :: System :: Filesystems
Requires-Python: >=3.8
License-File: LICENSE
Dynamic: license-file
